spider_core/__init__.py
spider_core/cli_spider.py
spider_core/project.md
spider_core/base/__init__.py
spider_core/base/link_metadata.py
spider_core/base/page_result.py
spider_core/base/spider.py
spider_core/browser/__init__.py
spider_core/browser/browser_client.py
spider_core/browser/playwright_client.py
spider_core/core_utils/__init__.py
spider_core/core_utils/chunking.py
spider_core/core_utils/url_utils.py
spider_core/extractors/__init__.py
spider_core/extractors/deterministic_extractor.py
spider_core/goal/__init__.py
spider_core/goal/goal_planner.py
spider_core/llm/__init__.py
spider_core/llm/embeddings_client.py
spider_core/llm/llm_client.py
spider_core/llm/openai_gpt_client.py
spider_core/llm/relevance_ranker.py
spider_core/spiders/__init__.py
spider_core/spiders/basic_spider.py
spider_core/spiders/goal_spider.py
spider_core/spiders/stealth/__init__.py
spider_core/spiders/stealth/stealth_config.py
spider_core/spiders/stealth/stealth_spider.py
spider_core/spiders/stealth/vpn_manager.py
spider_core/storage/__init__.py
spider_core/storage/db.py
spider_core/test/test.py
spider_core/test/test2.py
spider_core/test/test3.py
spider_core/test/test4.py
spider_core/test/test_ranker.py
spider_core/test/test_spider.py
go_spider-0.1.0.dist-info/METADATA
go_spider-0.1.0.dist-info/WHEEL
go_spider-0.1.0.dist-info/entry_points.txt
go_spider-0.1.0.dist-info/top_level.txt
go_spider-0.1.0.dist-info/RECORD
