Metadata-Version: 2.4
Name: go-spider
Version: 0.1.0
Summary: LLM-driven intelligent web spider with goal-oriented crawling and stealth capabilities.
Author: Josh Gompert
License-Expression: MIT
Requires-Python: >=3.10
Requires-Dist: playwright>=1.42.0
Requires-Dist: openai>=1.3.0
Requires-Dist: pydantic>=2.5.0
Requires-Dist: beautifulsoup4>=4.12.0
Requires-Dist: lxml>=4.9.3
Requires-Dist: tiktoken>=0.6.0
Requires-Dist: numpy>=1.26.0
